uiautomator/__init__.py
uiautomator/chromdriver.py
uiautomator/comparison.py
uiautomator/find_img.py
uiautomator/imgUtil.py
uiautomator/test.py
uiautomator/libs/app-uiautomator-test.apk
uiautomator/libs/app-uiautomator.apk
uiautomator/libs/bundle.jar
uiautomator/libs/uiautomator-stub.jar
atc_uiautomator-0.7.3.dist-info/LICENSE
atc_uiautomator-0.7.3.dist-info/METADATA
atc_uiautomator-0.7.3.dist-info/NOTICE
atc_uiautomator-0.7.3.dist-info/WHEEL
atc_uiautomator-0.7.3.dist-info/top_level.txt
atc_uiautomator-0.7.3.dist-info/RECORD
